stigg_sidecar_sdk/__init__.py
stigg_sidecar_sdk/certs/root-ca.pem
stigg_sidecar_sdk/generated/__init__.py
stigg_sidecar_sdk/generated/stigg/__init__.py
stigg_sidecar_sdk/generated/stigg/sidecar/__init__.py
stigg_sidecar_sdk/generated/stigg/sidecar/v1/__init__.py
stigg_sidecar_sdk/sdk.py
stigg_sidecar_sdk-5.132.0.dist-info/LICENSE
stigg_sidecar_sdk-5.132.0.dist-info/METADATA
stigg_sidecar_sdk-5.132.0.dist-info/WHEEL
stigg_sidecar_sdk-5.132.0.dist-info/RECORD
