Metadata-Version: 2.1
Name: stigg-sidecar-sdk
Version: 5.132.0
Summary: 
Author: Stigg
Author-email: support@stigg.io
Requires-Python: >=3.9,<4.0
Classifier: Programming Language :: Python :: 3
Classifier: Programming Language :: Python :: 3.9
Classifier: Programming Language :: Python :: 3.10
Classifier: Programming Language :: Python :: 3.11
Requires-Dist: betterproto[compiler] (==2.0.0b6)
Requires-Dist: stigg-api-client-v2
